[
  {
    "pos": 1,
    "name": "justMaki",
    "time": 22.79328,
    "round": null,
    "note": "winner"
  },
  {
    "pos": 2,
    "name": "RoundNzt",
    "time": 23.0477,
    "round": 17,
    "note": "cotd"
  },
  {
    "pos": 3,
    "name": "Mμ",
    "time": 22.51283,
    "round": 16,
    "note": "cotd"
  },
  {
    "pos": 4,
    "name": "[MMM]LKat",
    "time": 23.13792,
    "round": 15,
    "note": "cotd"
  },
  {
    "pos": 5,
    "name": "[KURK] Quickracer10",
    "time": 22.877,
    "round": 14,
    "note": "cotd"
  },
  {
    "pos": 6,
    "name": "[ZET]Stick",
    "time": 23.4381,
    "round": 13,
    "note": "cotd"
  },
  {
    "pos": 7,
    "name": "ZOMAN",
    "time": 22.73076,
    "round": 12,
    "note": "cotd"
  },
  {
    "pos": 8,
    "name": "[old]Warsnac",
    "time": 22.80124,
    "round": 12,
    "note": "cotd"
  },
  {
    "pos": 9,
    "name": "[MMM]Victor",
    "time": 23.3707,
    "round": 11,
    "note": "cotd"
  },
  {
    "pos": 10,
    "name": "M4rv",
    "time": 23.3711,
    "round": 11,
    "note": "cotd"
  },
  {
    "pos": 11,
    "name": "[CSC] redal",
    "time": 22.8017,
    "round": 10,
    "note": "cotd"
  },
  {
    "pos": 12,
    "name": "JakeAdjacent",
    "time": 22.80917,
    "round": 10,
    "note": "cotd"
  },
  {
    "pos": 13,
    "name": "brrryy",
    "time": 23.45816,
    "round": 9,
    "note": "cotd"
  },
  {
    "pos": 14,
    "name": "[CSC] Shadynook",
    "time": 23.561,
    "round": 9,
    "note": "cotd"
  },
  {
    "pos": 15,
    "name": "Gimpel",
    "time": 23.56133,
    "round": 9,
    "note": "cotd"
  },
  {
    "pos": 16,
    "name": "ping",
    "time": 23.08948,
    "round": 8,
    "note": "cotd"
  },
  {
    "pos": 17,
    "name": "Eclipse135",
    "time": 23.2988,
    "round": 8,
    "note": "cotd"
  },
  {
    "pos": 18,
    "name": "PlusMicron",
    "time": 23.43837,
    "round": 8,
    "note": "cotd"
  },
  {
    "pos": 19,
    "name": "Six",
    "time": 23.61832,
    "round": 7,
    "note": "cotd"
  },
  {
    "pos": 20,
    "name": "[20x]K410K3N",
    "time": 23.72749,
    "round": 7,
    "note": "cotd"
  },
  {
    "pos": 21,
    "name": "Jorts",
    "time": 23.98973,
    "round": 7,
    "note": "cotd"
  },
  {
    "pos": 22,
    "name": "aizpun",
    "time": 23.98045,
    "round": 6,
    "note": "cotd"
  },
  {
    "pos": 23,
    "name": "Savage Package",
    "time": 24.14152,
    "round": 6,
    "note": "cotd"
  },
  {
    "pos": 24,
    "name": "MALIYO",
    "time": null,
    "round": 6,
    "note": "dnf"
  },
  {
    "pos": 25,
    "name": "M4DSCOTSM4N",
    "time": 23.97011,
    "round": 5,
    "note": "cotd"
  },
  {
    "pos": 26,
    "name": "[Fenn]Lilly Fenn",
    "time": 24.4113,
    "round": 5,
    "note": "cotd"
  },
  {
    "pos": 27,
    "name": "[CSC]ShyGirlyRaccoon",
    "time": 24.64793,
    "round": 5,
    "note": "cotd"
  },
  {
    "pos": 28,
    "name": "Waaksaam",
    "time": 24.508,
    "round": 4,
    "note": "cotd"
  },
  {
    "pos": 29,
    "name": "Noxitu",
    "time": 24.579,
    "round": 4,
    "note": "LIVE_OVERRIDE_DNF"
  },
  {
    "pos": 30,
    "name": "Matic_D",
    "time": 24.62424,
    "round": 4,
    "note": "cotd"
  },
  {
    "pos": 31,
    "name": "wokonbike",
    "time": 24.22108,
    "round": 3,
    "note": "cotd"
  },
  {
    "pos": 32,
    "name": "Hi Im Yolo",
    "time": 24.30262,
    "round": 3,
    "note": "cotd"
  },
  {
    "pos": 33,
    "name": "[ZLOW] Milkaholic",
    "time": 24.617,
    "round": 3,
    "note": "cotd"
  },
  {
    "pos": 34,
    "name": "alpa",
    "time": 23.453,
    "round": 2,
    "note": "LIVE_OVERRIDE_DNF"
  },
  {
    "pos": 35,
    "name": "[MMM]Milk Man",
    "time": 26.02813,
    "round": 2,
    "note": "cotd"
  },
  {
    "pos": 36,
    "name": "ʇɐɔԀ",
    "time": 26.57833,
    "round": 2,
    "note": "cotd"
  },
  {
    "pos": 37,
    "name": "grop44",
    "time": 23.875,
    "round": 1,
    "note": "LIVE_OVERRIDE_DNF"
  },
  {
    "pos": 38,
    "name": "Towelie",
    "time": 25.62225,
    "round": 1,
    "note": "cotd"
  },
  {
    "pos": 39,
    "name": "[RABI]Yksdjcj",
    "time": 27.32678,
    "round": 1,
    "note": "cotd"
  }
]